c3/__init__.py
c3/_version.py
c3/create_containerless_operator.py
c3/create_gridwrapper.py
c3/create_operator.py
c3/notebook.py
c3/operator_utils.py
c3/parser.py
c3/pythonscript.py
c3/rscript.py
c3/utils.py
c3/templates/R_dockerfile_template
c3/templates/__init__.py
c3/templates/component_setup_code.R
c3/templates/component_setup_code.py
c3/templates/component_setup_code_wo_logging.py
c3/templates/cos_grid_wrapper_template.py
c3/templates/cwl_component_template.cwl
c3/templates/grid_wrapper_template.py
c3/templates/kfp_component_template.yaml
c3/templates/kubernetes_job_template.job.yaml
c3/templates/legacy_cos_grid_wrapper_template.py
c3/templates/python_dockerfile_template
c3/templates/s3kv_grid_wrapper_template.py
c3/templates/simple_grid_wrapper_template.py
claimed_c3-0.4.3.dist-info/LICENSE.txt
claimed_c3-0.4.3.dist-info/METADATA
claimed_c3-0.4.3.dist-info/WHEEL
claimed_c3-0.4.3.dist-info/entry_points.txt
claimed_c3-0.4.3.dist-info/top_level.txt
claimed_c3-0.4.3.dist-info/RECORD
