Metadata-Version: 2.2
Name: claimed-c3
Version: 0.4.3
Summary: The CLAIMED component compiler (C3) generates container images, KFP components, Kubernetes jobs, CWL Tasks, CLI applications
Author-email: The CLAIMED authors <claimed-framework@proton.me>
Maintainer: Benedikt Blumenstiel
Maintainer-email: Romeo Kienzler <claimed-framework@proton.me>
License: 
Project-URL: Homepage, https://github.com/claimed-framework/c3
Project-URL: Bug Tracker, https://github.com/claimed-framework/c3/issues
Keywords: CLAIMED,compiler,KubeFlow,Kubernetes
Classifier: Programming Language :: Python :: 3
Classifier: License :: OSI Approved :: Apache Software License
Classifier: Operating System :: OS Independent
Requires-Python: >=3.7
License-File: LICENSE.txt
Requires-Dist: nbconvert>=7.9.2
Requires-Dist: ipython>=8.16.1
Requires-Dist: traitlets>=5.11.2
Requires-Dist: pandas
